library/__init__.py
library/carinsurance_exception.py
library/date_util.py
library/document_helper.py
library/insurance_calculator.py
library/validate.py
library/exception/__init__.py
library/exception/document_exception.py
library/exception/user_exception.py
tests/__init__.py
tests/test_validate.py
x23101082_car_insurance-1.0.2.dist-info/LICENSE
x23101082_car_insurance-1.0.2.dist-info/LICENSE.txt
x23101082_car_insurance-1.0.2.dist-info/METADATA
x23101082_car_insurance-1.0.2.dist-info/WHEEL
x23101082_car_insurance-1.0.2.dist-info/top_level.txt
x23101082_car_insurance-1.0.2.dist-info/RECORD
