Metadata-Version: 2.1
Name: x23101082-car-insurance
Version: 1.0.2
Summary: Car Insurance Library
Home-page: https://github.com/raavihimavanth23/x23101083_carinsurance
Author: himavanthraavi23
Author-email: himavanthraavi23@gmai.com
License: UNKNOWN
Platform: UNKNOWN
Classifier: Programming Language :: Python :: 3
Classifier: License :: OSI Approved :: MIT License
Classifier: Operating System :: OS Independent
Requires-Python: >=3.6
License-File: LICENSE
License-File: LICENSE.txt
